wield/control/__init__.py
wield/control/_version.py
wield/control/plotting.py
wield/control/string_tuple_keys.py
wield/control/AAA/AAA.py
wield/control/AAA/__init__.py
wield/control/AAA/_version.py
wield/control/AAA/test/test_AAA.py
wield/control/AAA/test/test_AAA_algo.py
wield/control/AAA/test/test_AAA_present.py
wield/control/ACE/ACE.py
wield/control/ACE/ace_electrical.py
wield/control/ACE/ace_optical.py
wield/control/ACE/tupleize.py
wield/control/ACE/test/test_electronics.py
wield/control/ACE/test/test_lqe.py
wield/control/ACE/test/test_reduce.py
wield/control/ACE/test/test_statespace.py
wield/control/MIMO/__init__.py
wield/control/MIMO/mimo.py
wield/control/MIMO/response.py
wield/control/MIMO/ss.py
wield/control/MIMO/util.py
wield/control/MIMO/test/__init__.py
wield/control/MIMO/test/test_MIMO_build.py
wield/control/MIMO/test/HSTS/HSTS_build.py
wield/control/MIMO/test/HSTS/__init__.py
wield/control/MIMO/test/HSTS/readFilter.py
wield/control/MIMOtable/MIMOtable.py
wield/control/MIMOtable/__init__.py
wield/control/SFLU/SFLU.py
wield/control/SFLU/SFLUcompute.py
wield/control/SFLU/__init__.py
wield/control/SFLU/conversions.py
wield/control/SFLU/functions.py
wield/control/SFLU/nx2tikz.py
wield/control/SFLU/optics.py
wield/control/SFLU/utilities.py
wield/control/SFLU/cytoscape_flask/cytoscape_test.py
wield/control/SFLU/test/T_SFLU.py
wield/control/SFLU/test/T_SFLU_DRFPMI.py
wield/control/SFLU/test/T_SFLU_DRFPMI_build.py
wield/control/SFLU/test/T_SFLU_FC.py
wield/control/SFLU/test/T_SFLU_OPODRFPMI.py
wield/control/SFLU/test/T_SFLU_nx.py
wield/control/SFLU/test/quantum_lib.py
wield/control/SISO/__init__.py
wield/control/SISO/design.py
wield/control/SISO/response.py
wield/control/SISO/siso.py
wield/control/SISO/ss.py
wield/control/SISO/util.py
wield/control/SISO/zpk.py
wield/control/SISO/zpk_d2c_c2d.py
wield/control/SISO/test/test_SISO_c2d.py
wield/control/SISO/test/test_SISO_conversion.py
wield/control/SISO/test/test_SISO_delay.py
wield.control-0.6.2.dist-info/Apache-2.0.txt
wield.control-0.6.2.dist-info/BSD-3-Clause.txt
wield.control-0.6.2.dist-info/CC0-1.0.txt
wield.control-0.6.2.dist-info/METADATA
wield.control-0.6.2.dist-info/NOTICE
wield.control-0.6.2.dist-info/WHEEL
wield.control-0.6.2.dist-info/top_level.txt
wield.control-0.6.2.dist-info/RECORD
